PWE_CLI/__init__.py
PWE_CLI/helper.py
PWE_CLI/PWE_CLI_Scripts/__init__.py
PWE_CLI-0.0.3.data/scripts/pwe-cli
PWE_CLI-0.0.3.data/scripts/pwe_complexity_calc
PWE_CLI-0.0.3.data/scripts/pwe_dist_calc
PWE_CLI-0.0.3.data/scripts/pwe_export
PWE_CLI-0.0.3.data/scripts/pwe_load_worlds
PWE_CLI-0.0.3.data/scripts/pwe_query
PWE_CLI-0.0.3.data/scripts/pwe_run_clingo
PWE_CLI-0.0.3.data/scripts/pwe_run_dlv
PWE_CLI-0.0.3.data/scripts/pwe_visualize
PWE_CLI-0.0.3.dist-info/LICENSE
PWE_CLI-0.0.3.dist-info/METADATA
PWE_CLI-0.0.3.dist-info/WHEEL
PWE_CLI-0.0.3.dist-info/top_level.txt
PWE_CLI-0.0.3.dist-info/RECORD
