Metadata-Version: 2.1
Name: PWE-CLI
Version: 0.0.3
Summary: A CLI Interface to the Possible Worlds Explorer
Home-page: https://github.com/idaks/PWE-CLI
Author: Sahil Gupta
Author-email: 
License: UNKNOWN
Platform: UNKNOWN
Classifier: Programming Language :: Python :: 3
Classifier: License :: OSI Approved :: MIT License
Classifier: Operating System :: OS Independent
Requires-Dist: PW-explorer (>=0.0.23)
Requires-Dist: argparse (>=1.4.0)
Requires-Dist: pyparsing (>=2.2.0)
Requires-Dist: numpy (>=1.14.2)
Requires-Dist: subprocess32 (>=3.2.7)
